aqudem/__init__.py
aqudem/aqudem.py
aqudem/cross_correlation_helper.py
aqudem/damerau_levenshtein_helper.py
aqudem/event_analysis_helper.py
aqudem/two_set_helper.py
aqudem/utils.py
aqudem/ward_helper.py
aqudem-0.3.0.dist-info/licenses/AUTHORS.rst
aqudem-0.3.0.dist-info/licenses/LICENSE
aqudem-0.3.0.dist-info/METADATA
aqudem-0.3.0.dist-info/WHEEL
aqudem-0.3.0.dist-info/top_level.txt
aqudem-0.3.0.dist-info/RECORD
