Metadata-Version: 2.4
Name: aqudem
Version: 0.3.0
Summary: Activity and Sequence Detection Performance Measures: A package to evaluate activity detection results, including the sequence of events given multiple activity types.
Home-page: https://github.com/ics-unisg/aqudem
Author: ICS, Universität St. Gallen
Author-email: aaron.kurz@unisg.ch
License: GNU General Public License v3 or later (GPLv3+)
Project-URL: Documentation, https://aqudem.readthedocs.io
Project-URL: Bug Tracker, https://github.com/ics-unisg/aqudem/issues
Keywords: activity detection,sequence detection,performance measures,activity recognition,sequence recognition
Classifier: Development Status :: 4 - Beta
Classifier: Intended Audience :: Science/Research
Classifier: License :: OSI Approved :: GNU General Public License v3 or later (GPLv3+)
Classifier: Programming Language :: Python :: 3.12
Classifier: Topic :: Scientific/Engineering :: Information Analysis
Requires-Python: >=3.12
License-File: LICENSE
License-File: AUTHORS.rst
Requires-Dist: pm4py~=2.7.15.1
Requires-Dist: textdistance~=4.6.3
Requires-Dist: typing-extensions~=4.13.2
Requires-Dist: numpy~=2.2.5
Requires-Dist: matplotlib~=3.10.1
Requires-Dist: static-frame~=2.18.1
Provides-Extra: testing
Requires-Dist: pytest>=3; extra == "testing"
Dynamic: license-file
